powersearch_mcp/__init__.py
powersearch_mcp/_version.py
powersearch_mcp/app.py
powersearch_mcp/authorization_middleware.py
powersearch_mcp/powersearch.py
powersearch_mcp/settings.py
powersearch_mcp/summarize.py
powersearch_mcp-0.4.0.dist-info/METADATA
powersearch_mcp-0.4.0.dist-info/WHEEL
powersearch_mcp-0.4.0.dist-info/licenses/LICENSE
powersearch_mcp-0.4.0.dist-info/RECORD
