Metadata-Version: 2.4
Name: powersearch-mcp
Version: 0.4.0
Summary: PowerSearch MCP helps AI agents search and retrieve content from the public web with fewer broken fetches and clean, AI-friendly outputs ready to cite.
Project-URL: Homepage, https://github.com/theobjectivedad/powersearch-mcp
Project-URL: Issues, https://github.com/theobjectivedad/powersearch-mcp/issues
Project-URL: Changelog, https://github.com/theobjectivedad/powersearch-mcp/releases
Author-email: The Objective Dad <theobjectivedad@pm.me>
License:                                  Apache License
License-File: LICENSE
Keywords: agents,mcp,retrieval,scraping,search,web
Classifier: Development Status :: 4 - Beta
Classifier: Intended Audience :: Developers
Classifier: License :: OSI Approved :: Apache Software License
Classifier: Natural Language :: English
Classifier: Operating System :: OS Independent
Classifier: Programming Language :: Python :: 3
Classifier: Programming Language :: Python :: 3 :: Only
Classifier: Programming Language :: Python :: 3.13
Classifier: Topic :: Internet :: WWW/HTTP :: Indexing/Search
Classifier: Topic :: Scientific/Engineering :: Artificial Intelligence
Requires-Python: >=3.13
Requires-Dist: curl-cffi<1,>=0.14.0
Requires-Dist: eunomia-mcp>=0.3.10
Requires-Dist: fastmcp[openai]<3,>=2.14
Requires-Dist: httpx[http2]<1,>=0.28.1
Requires-Dist: mcp[cli]<2,>=1.12.1
Requires-Dist: msgspec<1,>=0.20.0
Requires-Dist: numpy<3,>=2.4.0
Requires-Dist: py-key-value-aio[disk,memory,redis]<1,>=0.3.0
Requires-Dist: pydantic-settings<3,>=2.7.0
Requires-Dist: pydantic<3,>=2.12.5
Requires-Dist: scrapling[all]<2,>=0.3.14
Requires-Dist: trafilatura<3,>=2.0.0
Requires-Dist: truststore<1,>=0.10.4
Requires-Dist: uvicorn<1,>=0.40.0
